[{"ai_address":"北京市海淀区中关村大街1号","ai_email":"zhangsan@example.com","ai_name":"张三","ai_phone":"13800138000","uuid":"123e4567-e89b-4d17-b742-f876e877a064"},{"ai_address":"上海市徐汇区漕溪路200号","ai_email":"lisi@example.com","ai_name":"李四","ai_phone":"13900139000","uuid":"456f789a-bcde-4fgh-9ijk-890jklmnpqr01"},{"ai_address":"广州市天河区黄埔大道西76号","ai_email":"wangwu@example.com","ai_name":"王五","ai_phone":"13700137000","uuid":"789a0bcd-e1f2-4g3h-9ijk-234567890abc"},{"ai_address":"深圳市南山区科技园科兴路16号","ai_email":"zhaoliu@example.com","ai_name":"赵六","ai_phone":"13600136000","uuid":"abcde1234-fghi-4jkl-56mn-67890bcdefgh"},{"ai_address":"成都市高新区天府大道北段289号","ai_email":"qianqi@example.com","ai_name":"钱七","ai_phone":"13500135000","uuid":"defgh1234-56ij-4klm-78no-890bcdefghij"}]